desper/__init__.py
desper/bisect.py
desper/events.py
desper/loop.py
desper/math.py
desper/logic/__init__.py
desper/logic/coroutines.py
desper/logic/spatial.py
desper/logic/world.py
desper/model/__init__.py
desper/model/tree.py
desper/model/world.py
desper-1.1.1.post0.dist-info/LICENSE
desper-1.1.1.post0.dist-info/METADATA
desper-1.1.1.post0.dist-info/WHEEL
desper-1.1.1.post0.dist-info/top_level.txt
desper-1.1.1.post0.dist-info/RECORD
