Metadata-Version: 2.1
Name: desper
Version: 1.1.1.post0
Summary: A Python3 game development toolkit for resource and logic management
Home-page: http://github.com/Ball-Man/desper
Author: Francesco Mistri
Author-email: franc.mistri@gmail.com
License: MIT
Classifier: Intended Audience :: Developers
Classifier: Programming Language :: Python :: 3 :: Only
Classifier: Topic :: Games/Entertainment
Requires-Python: >=3.9
License-File: LICENSE
